__init__.py
bitrixogram/__init__.py
bitrixogram/attach.py
bitrixogram/core.py
bitrixogram/keyboard.py
bitrixogram-1.0.7.dist-info/LICENSE
bitrixogram-1.0.7.dist-info/METADATA
bitrixogram-1.0.7.dist-info/WHEEL
bitrixogram-1.0.7.dist-info/top_level.txt
bitrixogram-1.0.7.dist-info/RECORD
