Metadata-Version: 2.2
Name: bitrixogram
Version: 1.0.7
Summary: A simple async framework for creating Bitrix24 chat bots in 'aiogram'-like style over Bitrix24 REST API
Author-email: Aleksey Rublev <lexx@rcbd.org>
Project-URL: Homepage, https://github.com/lxxr/bitrixogram
Project-URL: Issues, https://github.com/lxxr/bitrixogram/issues
Classifier: Programming Language :: Python :: 3
Classifier: License :: OSI Approved :: MIT License
Classifier: Operating System :: OS Independent
Requires-Python: >=3.8
License-File: LICENSE
